{
	"name": "PagePort",
	"version": "1.0.0",
	"author": [
		"WikiWorks team"
	],
	"url": "https://www.mediawiki.org/wiki/Extension:PagePort",
	"descriptionmsg": "pageport-desc",
	"license-name": "MIT",
	"requires": {
		"MediaWiki": ">= 1.30.0"
	},
	"type": "other",
	"AutoloadClasses": {
		"PagePortHooks": "PagePortHooks.php",
		"PagePort": "includes/PagePort.php"
	},
	"config": {},
	"ExtensionMessagesFiles": {
		"PagePortAlias": "PagePort.i18n.alias.php"
	},
	"Hooks": {},
	"MessagesDirs": {
		"PagePort": [
			"i18n"
		]
	},
	"ResourceModules": {},
	"ResourceFileModulePaths": {
		"localBasePath": "",
		"remoteExtPath": "PagePort"
	},
	"manifest_version": 2
}
